{
  "compilerOptions": {
    "allowSyntheticDefaultImports": true,
    "composite": true,
    "declaration": true,
    "emitDeclarationOnly": true,
    "esModuleInterop": true,
    "importsNotUsedAsValues": "error",
    "isolatedModules": true,
    "lib": ["dom", "esnext"],
    "module": "esnext",
    "moduleResolution": "node",
    "noFallthroughCasesInSwitch": true,
    "noImplicitReturns": true,
    "noUnusedLocals": true,
    "noUnusedParameters": true,
    "resolveJsonModule": true,
    "strict": true,
    "target": "es2017"
  },
  "exclude": ["**/node_modules/**/*", "**/.turbo/**/*", "**/test/**/*", "**/dist/**/*"]
}
